rmcp/__init__.py
rmcp/bidirectional.py
rmcp/cli.py
rmcp/config/__init__.py
rmcp/config/defaults.py
rmcp/config/loader.py
rmcp/config/models.py
rmcp/config/schema.py
rmcp/core/__init__.py
rmcp/core/context.py
rmcp/core/schemas.py
rmcp/core/server.py
rmcp/discovery.py
rmcp/exceptions.py
rmcp/logging_config.py
rmcp/py.typed
rmcp/r_assets/.Rbuildignore
rmcp/r_assets/.lintr
rmcp/r_assets/DESCRIPTION
rmcp/r_assets/NAMESPACE
rmcp/r_assets/R/utils.R
rmcp/r_assets/README.md
rmcp/r_assets/__init__.py
rmcp/r_assets/build_docs.R
rmcp/r_assets/common/formatting.R
rmcp/r_assets/common/script_template.R
rmcp/r_assets/format_r.R
rmcp/r_assets/lint_r.R
rmcp/r_assets/loader.py
rmcp/r_assets/run_tests.R
rmcp/r_assets/scripts/descriptive/frequency_table.R
rmcp/r_assets/scripts/descriptive/outlier_detection.R
rmcp/r_assets/scripts/descriptive/summary_stats.R
rmcp/r_assets/scripts/econometrics/instrumental_variables.R
rmcp/r_assets/scripts/econometrics/panel_regression.R
rmcp/r_assets/scripts/econometrics/var_model.R
rmcp/r_assets/scripts/fileops/data_info.R
rmcp/r_assets/scripts/fileops/filter_data.R
rmcp/r_assets/scripts/fileops/read_csv.R
rmcp/r_assets/scripts/fileops/read_excel.R
rmcp/r_assets/scripts/fileops/read_json.R
rmcp/r_assets/scripts/fileops/write_csv.R
rmcp/r_assets/scripts/fileops/write_excel.R
rmcp/r_assets/scripts/fileops/write_json.R
rmcp/r_assets/scripts/formula_builder/validate_formula.R
rmcp/r_assets/scripts/helpers/analyze_data_for_errors.R
rmcp/r_assets/scripts/helpers/load_example.R
rmcp/r_assets/scripts/helpers/validate_data.R
rmcp/r_assets/scripts/machine_learning/decision_tree.R
rmcp/r_assets/scripts/machine_learning/kmeans_clustering.R
rmcp/r_assets/scripts/machine_learning/random_forest.R
rmcp/r_assets/scripts/regression/correlation_analysis.R
rmcp/r_assets/scripts/regression/linear_model.R
rmcp/r_assets/scripts/regression/logistic_regression.R
rmcp/r_assets/scripts/statistical_tests/anova.R
rmcp/r_assets/scripts/statistical_tests/chi_square_test.R
rmcp-0.8.1.dist-info/WHEEL
rmcp-0.8.1.dist-info/entry_points.txt
rmcp-0.8.1.dist-info/METADATA
rmcp-0.8.1.dist-info/RECORD
