Metadata-Version: 2.3
Name: rmcp
Version: 0.8.1
Summary: Comprehensive Model Context Protocol server with 52 statistical analysis tools for Claude Desktop and Claude web, featuring HTTP transport, interactive documentation, and production deployment
Keywords: mcp,r,statistics,econometrics,model-context-protocol,data-analysis,http,fastapi,sse,configuration,claude-web,connector,anthropic
Author: Gaurav Sood
Author-email: Gaurav Sood <gsood07@gmail.com>
License: MIT
Classifier: Development Status :: 4 - Beta
Classifier: Intended Audience :: Developers
Classifier: Intended Audience :: Science/Research
Classifier: License :: OSI Approved :: MIT License
Classifier: Operating System :: OS Independent
Classifier: Programming Language :: Python :: 3
Classifier: Programming Language :: Python :: 3.11
Classifier: Programming Language :: Python :: 3.12
Classifier: Programming Language :: Python :: 3.13
Classifier: Programming Language :: R
Classifier: Topic :: Scientific/Engineering :: Information Analysis
Classifier: Topic :: Software Development :: Libraries :: Python Modules
Classifier: Topic :: System :: Distributed Computing
Requires-Dist: click>=8.1.0
Requires-Dist: jsonschema>=4.0.0
Requires-Dist: psutil>=5.0.0
Requires-Dist: structlog>=23.1.0
Requires-Dist: fastapi>=0.100.0 ; extra == 'all'
Requires-Dist: uvicorn>=0.20.0 ; extra == 'all'
Requires-Dist: sse-starlette>=1.6.0 ; extra == 'all'
Requires-Dist: httpx>=0.25.0 ; extra == 'all'
Requires-Dist: pandas>=1.5.0 ; extra == 'all'
Requires-Dist: openpyxl>=3.0.0 ; extra == 'all'
Requires-Dist: fastapi>=0.100.0 ; extra == 'http'
Requires-Dist: uvicorn>=0.20.0 ; extra == 'http'
Requires-Dist: sse-starlette>=1.6.0 ; extra == 'http'
Requires-Dist: httpx>=0.25.0 ; extra == 'http'
Requires-Dist: pandas>=1.5.0 ; extra == 'http'
Requires-Dist: openpyxl>=3.0.0 ; extra == 'http'
Requires-Python: >=3.11
Project-URL: Documentation, https://github.com/finite-sample/rmcp#readme
Project-URL: Homepage, https://github.com/finite-sample/rmcp
Project-URL: Issues, https://github.com/finite-sample/rmcp/issues
Project-URL: Repository, https://github.com/finite-sample/rmcp
Provides-Extra: all
Provides-Extra: http
